impromptu
