Metadata-Version: 1.1
Name: Impromptu
Version: 0.2
Summary: A graphical teleprompter-like scrolling HTML text display
Home-page: http://chrisarndt.de/projects/impromptu/
Author: Christopher Arndt
Author-email: chris@chrisarndt.de
License: MIT License
Download-URL: http://chrisarndt.de/projects/impromptu/download/
Keywords: html,pyglet,gui,scrolling
Platform: POSIX
Platform: Windows
Platform: MacOS X
Classifier: Development Status :: 5 - Production/Stable
Classifier: Environment :: MacOS X
Classifier: Environment :: Win32 (MS Windows)
Classifier: Environment :: X11 Applications
Classifier: Intended Audience :: Education
Classifier: Intended Audience :: End Users/Desktop
Classifier: License :: OSI Approved :: Python Software Foundation License
Classifier: Operating System :: Microsoft :: Windows
Classifier: Operating System :: POSIX
Classifier: Operating System :: MacOS :: MacOS X
Classifier: Programming Language :: Python
Classifier: Topic :: Education
Classifier: Topic :: Multimedia :: Graphics :: Presentation
